{
  "id": "184e3b58-cb42-460d-b3b8-6807200e3ab0",
  "prevId": "7d788003-6936-477d-a388-f26aad00db40",
  "version": "7",
  "dialect": "postgresql",
  "tables": {
    "agape_app_demo_development.access_employee": {
      "name": "access_employee",
      "schema": "agape_app_demo_development",
      "columns": {
        "id": {
          "name": "id",
          "type": "serial",
          "primaryKey": true,
          "notNull": true
        },
        "employee_id": {
          "name": "employee_id",
          "type": "integer",
          "primaryKey": false,
          "notNull": true
        },
        "username": {
          "name": "username",
          "type": "varchar(64)",
          "primaryKey": false,
          "notNull": true
        },
        "password_hash": {
          "name": "password_hash",
          "type": "text",
          "primaryKey": false,
          "notNull": true
        },
        "is_active": {
          "name": "is_active",
          "type": "boolean",
          "primaryKey": false,
          "notNull": true,
          "default": true
        },
        "is_locked": {
          "name": "is_locked",
          "type": "boolean",
          "primaryKey": false,
          "notNull": true,
          "default": false
        },
        "last_login": {
          "name": "last_login",
          "type": "timestamp with time zone",
          "primaryKey": false,
          "notNull": false
        },
        "created_at": {
          "name": "created_at",
          "type": "timestamp with time zone",
          "primaryKey": false,
          "notNull": true,
          "default": "now()"
        },
        "updated_at": {
          "name": "updated_at",
          "type": "timestamp with time zone",
          "primaryKey": false,
          "notNull": false,
          "default": "now()"
        }
      },
      "indexes": {},
      "foreignKeys": {
        "access_employee_employee_id_staff_employee_id_fk": {
          "name": "access_employee_employee_id_staff_employee_id_fk",
          "tableFrom": "access_employee",
          "tableTo": "staff_employee",
          "schemaTo": "agape_app_demo_development",
          "columnsFrom": [
            "employee_id"
          ],
          "columnsTo": [
            "id"
          ],
          "onDelete": "no action",
          "onUpdate": "no action"
        }
      },
      "compositePrimaryKeys": {},
      "uniqueConstraints": {
        "access_employee_username_unique": {
          "name": "access_employee_username_unique",
          "nullsNotDistinct": false,
          "columns": [
            "username"
          ]
        }
      },
      "policies": {},
      "checkConstraints": {},
      "isRLSEnabled": false
    },
    "agape_app_demo_development.agape": {
      "name": "agape",
      "schema": "agape_app_demo_development",
      "columns": {
        "key": {
          "name": "key",
          "type": "text",
          "primaryKey": true,
          "notNull": true
        },
        "value": {
          "name": "value",
          "type": "jsonb",
          "primaryKey": false,
          "notNull": true
        },
        "created_at": {
          "name": "created_at",
          "type": "timestamp with time zone",
          "primaryKey": false,
          "notNull": false,
          "default": "now()"
        },
        "updated_at": {
          "name": "updated_at",
          "type": "timestamp with time zone",
          "primaryKey": false,
          "notNull": false,
          "default": "now()"
        }
      },
      "indexes": {},
      "foreignKeys": {},
      "compositePrimaryKeys": {},
      "uniqueConstraints": {},
      "policies": {},
      "checkConstraints": {},
      "isRLSEnabled": false
    },
    "agape_app_demo_development.inventory_categories": {
      "name": "inventory_categories",
      "schema": "agape_app_demo_development",
      "columns": {
        "id": {
          "name": "id",
          "type": "serial",
          "primaryKey": true,
          "notNull": true
        },
        "fullName": {
          "name": "fullName",
          "type": "varchar(50)",
          "primaryKey": false,
          "notNull": true
        },
        "isEnabled": {
          "name": "isEnabled",
          "type": "boolean",
          "primaryKey": false,
          "notNull": true
        }
      },
      "indexes": {},
      "foreignKeys": {},
      "compositePrimaryKeys": {},
      "uniqueConstraints": {},
      "policies": {},
      "checkConstraints": {},
      "isRLSEnabled": false
    },
    "agape_app_demo_development.inventory_product": {
      "name": "inventory_product",
      "schema": "agape_app_demo_development",
      "columns": {
        "id": {
          "name": "id",
          "type": "serial",
          "primaryKey": true,
          "notNull": true
        },
        "full_name": {
          "name": "full_name",
          "type": "varchar(80)",
          "primaryKey": false,
          "notNull": true
        },
        "slogan": {
          "name": "slogan",
          "type": "varchar(80)",
          "primaryKey": false,
          "notNull": true
        },
        "description": {
          "name": "description",
          "type": "varchar(500)",
          "primaryKey": false,
          "notNull": false
        },
        "is_active": {
          "name": "is_active",
          "type": "boolean",
          "primaryKey": false,
          "notNull": true
        },
        "rating": {
          "name": "rating",
          "type": "smallint",
          "primaryKey": false,
          "notNull": true
        },
        "price": {
          "name": "price",
          "type": "numeric(10, 2)",
          "primaryKey": false,
          "notNull": true
        },
        "category_id": {
          "name": "category_id",
          "type": "integer",
          "primaryKey": false,
          "notNull": true
        },
        "subcategory_id": {
          "name": "subcategory_id",
          "type": "integer",
          "primaryKey": false,
          "notNull": true
        },
        "images": {
          "name": "images",
          "type": "jsonb",
          "primaryKey": false,
          "notNull": true
        }
      },
      "indexes": {},
      "foreignKeys": {
        "inventory_product_category_id_inventory_categories_id_fk": {
          "name": "inventory_product_category_id_inventory_categories_id_fk",
          "tableFrom": "inventory_product",
          "tableTo": "inventory_categories",
          "schemaTo": "agape_app_demo_development",
          "columnsFrom": [
            "category_id"
          ],
          "columnsTo": [
            "id"
          ],
          "onDelete": "restrict",
          "onUpdate": "no action"
        },
        "inventory_product_subcategory_id_inventory_subcategories_id_fk": {
          "name": "inventory_product_subcategory_id_inventory_subcategories_id_fk",
          "tableFrom": "inventory_product",
          "tableTo": "inventory_subcategories",
          "schemaTo": "agape_app_demo_development",
          "columnsFrom": [
            "subcategory_id"
          ],
          "columnsTo": [
            "id"
          ],
          "onDelete": "restrict",
          "onUpdate": "no action"
        }
      },
      "compositePrimaryKeys": {},
      "uniqueConstraints": {},
      "policies": {},
      "checkConstraints": {},
      "isRLSEnabled": false
    },
    "agape_app_demo_development.inventory_subcategories": {
      "name": "inventory_subcategories",
      "schema": "agape_app_demo_development",
      "columns": {
        "id": {
          "name": "id",
          "type": "serial",
          "primaryKey": true,
          "notNull": true
        },
        "fullName": {
          "name": "fullName",
          "type": "varchar(50)",
          "primaryKey": false,
          "notNull": true
        },
        "isEnabled": {
          "name": "isEnabled",
          "type": "boolean",
          "primaryKey": false,
          "notNull": true
        },
        "categoryId": {
          "name": "categoryId",
          "type": "integer",
          "primaryKey": false,
          "notNull": true
        }
      },
      "indexes": {},
      "foreignKeys": {
        "inventory_subcategories_categoryId_inventory_categories_id_fk": {
          "name": "inventory_subcategories_categoryId_inventory_categories_id_fk",
          "tableFrom": "inventory_subcategories",
          "tableTo": "inventory_categories",
          "schemaTo": "agape_app_demo_development",
          "columnsFrom": [
            "categoryId"
          ],
          "columnsTo": [
            "id"
          ],
          "onDelete": "restrict",
          "onUpdate": "no action"
        }
      },
      "compositePrimaryKeys": {},
      "uniqueConstraints": {},
      "policies": {},
      "checkConstraints": {},
      "isRLSEnabled": false
    },
    "agape_app_demo_development.person": {
      "name": "person",
      "schema": "agape_app_demo_development",
      "columns": {
        "id": {
          "name": "id",
          "type": "serial",
          "primaryKey": true,
          "notNull": true
        },
        "first_name": {
          "name": "first_name",
          "type": "varchar(100)",
          "primaryKey": false,
          "notNull": true
        },
        "last_name": {
          "name": "last_name",
          "type": "varchar(100)",
          "primaryKey": false,
          "notNull": true
        },
        "birthdate": {
          "name": "birthdate",
          "type": "timestamp with time zone",
          "primaryKey": false,
          "notNull": true
        },
        "email": {
          "name": "email",
          "type": "varchar(255)",
          "primaryKey": false,
          "notNull": true
        },
        "phone": {
          "name": "phone",
          "type": "varchar(20)",
          "primaryKey": false,
          "notNull": false
        },
        "created_at": {
          "name": "created_at",
          "type": "timestamp with time zone",
          "primaryKey": false,
          "notNull": false,
          "default": "now()"
        },
        "updated_at": {
          "name": "updated_at",
          "type": "timestamp with time zone",
          "primaryKey": false,
          "notNull": false,
          "default": "now()"
        }
      },
      "indexes": {},
      "foreignKeys": {},
      "compositePrimaryKeys": {},
      "uniqueConstraints": {
        "person_email_unique": {
          "name": "person_email_unique",
          "nullsNotDistinct": false,
          "columns": [
            "email"
          ]
        }
      },
      "policies": {},
      "checkConstraints": {},
      "isRLSEnabled": false
    },
    "agape_app_demo_development.staff_employee": {
      "name": "staff_employee",
      "schema": "agape_app_demo_development",
      "columns": {
        "id": {
          "name": "id",
          "type": "serial",
          "primaryKey": true,
          "notNull": true
        },
        "person_id": {
          "name": "person_id",
          "type": "integer",
          "primaryKey": false,
          "notNull": true
        },
        "hire_date": {
          "name": "hire_date",
          "type": "timestamp with time zone",
          "primaryKey": false,
          "notNull": true,
          "default": "now()"
        },
        "is_active": {
          "name": "is_active",
          "type": "boolean",
          "primaryKey": false,
          "notNull": true,
          "default": true
        },
        "metadata": {
          "name": "metadata",
          "type": "jsonb",
          "primaryKey": false,
          "notNull": false
        },
        "avatar_url": {
          "name": "avatar_url",
          "type": "varchar(255)",
          "primaryKey": false,
          "notNull": true
        },
        "created_at": {
          "name": "created_at",
          "type": "timestamp with time zone",
          "primaryKey": false,
          "notNull": true,
          "default": "now()"
        },
        "updated_at": {
          "name": "updated_at",
          "type": "timestamp with time zone",
          "primaryKey": false,
          "notNull": false,
          "default": "now()"
        }
      },
      "indexes": {},
      "foreignKeys": {
        "staff_employee_person_id_person_id_fk": {
          "name": "staff_employee_person_id_person_id_fk",
          "tableFrom": "staff_employee",
          "tableTo": "person",
          "schemaTo": "agape_app_demo_development",
          "columnsFrom": [
            "person_id"
          ],
          "columnsTo": [
            "id"
          ],
          "onDelete": "no action",
          "onUpdate": "no action"
        }
      },
      "compositePrimaryKeys": {},
      "uniqueConstraints": {
        "staff_employee_person_id_unique": {
          "name": "staff_employee_person_id_unique",
          "nullsNotDistinct": false,
          "columns": [
            "person_id"
          ]
        }
      },
      "policies": {},
      "checkConstraints": {},
      "isRLSEnabled": false
    },
    "agape_app_demo_development.staff_employee_roles": {
      "name": "staff_employee_roles",
      "schema": "agape_app_demo_development",
      "columns": {
        "employee_id": {
          "name": "employee_id",
          "type": "integer",
          "primaryKey": false,
          "notNull": true
        },
        "role_id": {
          "name": "role_id",
          "type": "integer",
          "primaryKey": false,
          "notNull": true
        }
      },
      "indexes": {},
      "foreignKeys": {
        "staff_employee_roles_employee_id_staff_employee_id_fk": {
          "name": "staff_employee_roles_employee_id_staff_employee_id_fk",
          "tableFrom": "staff_employee_roles",
          "tableTo": "staff_employee",
          "schemaTo": "agape_app_demo_development",
          "columnsFrom": [
            "employee_id"
          ],
          "columnsTo": [
            "id"
          ],
          "onDelete": "no action",
          "onUpdate": "no action"
        },
        "staff_employee_roles_role_id_staff_role_id_fk": {
          "name": "staff_employee_roles_role_id_staff_role_id_fk",
          "tableFrom": "staff_employee_roles",
          "tableTo": "staff_role",
          "schemaTo": "agape_app_demo_development",
          "columnsFrom": [
            "role_id"
          ],
          "columnsTo": [
            "id"
          ],
          "onDelete": "no action",
          "onUpdate": "no action"
        }
      },
      "compositePrimaryKeys": {
        "staff_employee_roles_employee_id_role_id_pk": {
          "name": "staff_employee_roles_employee_id_role_id_pk",
          "columns": [
            "employee_id",
            "role_id"
          ]
        }
      },
      "uniqueConstraints": {},
      "policies": {},
      "checkConstraints": {},
      "isRLSEnabled": false
    },
    "agape_app_demo_development.staff_role": {
      "name": "staff_role",
      "schema": "agape_app_demo_development",
      "columns": {
        "id": {
          "name": "id",
          "type": "serial",
          "primaryKey": true,
          "notNull": true
        },
        "code": {
          "name": "code",
          "type": "varchar(10)",
          "primaryKey": false,
          "notNull": true
        },
        "name": {
          "name": "name",
          "type": "varchar(100)",
          "primaryKey": false,
          "notNull": true
        },
        "description": {
          "name": "description",
          "type": "text",
          "primaryKey": false,
          "notNull": false
        },
        "is_active": {
          "name": "is_active",
          "type": "boolean",
          "primaryKey": false,
          "notNull": true,
          "default": true
        },
        "created_at": {
          "name": "created_at",
          "type": "timestamp with time zone",
          "primaryKey": false,
          "notNull": false,
          "default": "now()"
        },
        "updated_at": {
          "name": "updated_at",
          "type": "timestamp with time zone",
          "primaryKey": false,
          "notNull": false,
          "default": "now()"
        }
      },
      "indexes": {},
      "foreignKeys": {},
      "compositePrimaryKeys": {},
      "uniqueConstraints": {},
      "policies": {},
      "checkConstraints": {},
      "isRLSEnabled": false
    }
  },
  "enums": {},
  "schemas": {
    "agape_app_demo_development": "agape_app_demo_development"
  },
  "sequences": {},
  "roles": {},
  "policies": {},
  "views": {},
  "_meta": {
    "columns": {},
    "schemas": {},
    "tables": {}
  }
}